odoo/addons/delivery_purchase_label/README.rst
odoo/addons/delivery_purchase_label/__init__.py
odoo/addons/delivery_purchase_label/__manifest__.py
odoo/addons/delivery_purchase_label/data/stock_picking_type.xml
odoo/addons/delivery_purchase_label/i18n/delivery_purchase_label.pot
odoo/addons/delivery_purchase_label/i18n/it.po
odoo/addons/delivery_purchase_label/models/__init__.py
odoo/addons/delivery_purchase_label/models/delivery_carrier.py
odoo/addons/delivery_purchase_label/models/mail_compose_message.py
odoo/addons/delivery_purchase_label/models/purchase_order.py
odoo/addons/delivery_purchase_label/models/stock_move.py
odoo/addons/delivery_purchase_label/models/stock_picking.py
odoo/addons/delivery_purchase_label/readme/CONFIGURE.rst
odoo/addons/delivery_purchase_label/readme/CONTRIBUTORS.rst
odoo/addons/delivery_purchase_label/readme/DESCRIPTION.rst
odoo/addons/delivery_purchase_label/static/description/icon.png
odoo/addons/delivery_purchase_label/static/description/index.html
odoo/addons/delivery_purchase_label/tests/__init__.py
odoo/addons/delivery_purchase_label/tests/test_delivery_purchase_label.py
odoo/addons/delivery_purchase_label/views/delivery_carrier.xml
odoo/addons/delivery_purchase_label/views/purchase_order_views.xml
odoo14_addon_delivery_purchase_label-14.0.1.1.0.dist-info/METADATA
odoo14_addon_delivery_purchase_label-14.0.1.1.0.dist-info/WHEEL
odoo14_addon_delivery_purchase_label-14.0.1.1.0.dist-info/top_level.txt
odoo14_addon_delivery_purchase_label-14.0.1.1.0.dist-info/RECORD
