Metadata-Version: 2.1
Name: odoo14-addon-delivery_purchase_label
Version: 14.0.1.1.0
Summary: Allows printing carrier delivery labels for a dropshipping vendor.
Home-page: https://github.com/OCA/delivery-carrier
Author: Camptocamp, BCIM, Odoo Community Association (OCA)
Author-email: support@odoo-community.org
License: AGPL-3
Classifier: Programming Language :: Python
Classifier: Framework :: Odoo
Classifier: Framework :: Odoo :: 14.0
Classifier: License :: OSI Approved :: GNU Affero General Public License v3
Requires-Python: >=3.6
Requires-Dist: odoo<14.1dev,>=14.0a
